three_to_one_mux.v
`timescale 1ns / 1ns
module three_to_one_mux(d0,d1,d2,s,y);
input [15:0] d0, d1, d2;
input [1:0] s;
output [15:0] y;
reg [15:0] y;

always@(d0 or d1 or d2 or s)
begin
case(s)
      2'b00  : y = d0;
      2'b01  : y = d1;
      2'b10  : y = d2;
      default : y = d0; 
endcase
end
endmodule

rotate.v
module rotate_right(n, value, result);
	input [15:0] n, value;
	output reg [15:0] result;
	reg [15:0] temp, temp2;
	
	always@(*)
	begin
		case(n[3:0])
			0:
				begin
				result <= value;
				end
			1:
				begin
				temp <= { {15 - 1 + 1{1'b0}}, value[1 - 1: 0] };
				temp2 <= value >> 1;
				result <= {temp[1 - 1: 0] , temp2[15 - 1: 0]};
				end
			2:
				begin
				temp <= { {15 - 2 + 1{1'b0}}, value[2 - 1: 0] };
				temp2 <= value >> 2;
				result <= {temp[2 - 1: 0] , temp2[15 - 2: 0]};
				end
			3:
				begin
				temp <= { {15 - 3 + 1{1'b0}}, value[3 - 1: 0] };
				temp2 <= value >> 3;
				result <= {temp[3 - 1: 0] , temp2[15 - 3: 0]};
				end
			4:
				begin
				temp <= { {15 - 4 + 1{1'b0}}, value[4 - 1: 0] };
				temp2 <= value >> 4;
				result <= {temp[4 - 1: 0] , temp2[15 - 4: 0]};
				end
			5:
				begin
				temp <= { {15 - 5 + 1{1'b0}}, value[5 - 1: 0] };
				temp2 <= value >> 5;
				result <= {temp[5 - 1: 0] , temp2[15 - 5: 0]};
				end
			6:
				begin
				temp <= { {15 - 6 + 1{1'b0}}, value[6 - 1: 0] };
				temp2 <= value >> 6;
				result <= {temp[6 - 1: 0] , temp2[15 - 6: 0]};
				end
			7:
				begin
				temp <= { {15 - 7 + 1{1'b0}}, value[7 - 1: 0] };
				temp2 <= value >> 7;
				result <= {temp[7 - 1: 0] , temp2[15 - 7: 0]};
				end
			8:
				begin
				temp <= { {15 - 8 + 1{1'b0}}, value[8 - 1: 0] };
				temp2 <= value >> 8;
				result <= {temp[8 - 1: 0] , temp2[15 - 8: 0]};
				end
			9:
				begin
				temp <= { {15 - 9 + 1{1'b0}}, value[9 - 1: 0] };
				temp2 <= value >> 9;
				result <= {temp[9 - 1: 0] , temp2[15 - 9: 0]};
				end
			10:
				begin
				temp <= { {15 - 10 + 1{1'b0}}, value[10 - 1: 0] };
				temp2 <= value >> 10;
				result <= {temp[10 - 1: 0] , temp2[15 - 10: 0]};
				end
			11:
				begin
				temp <= { {15 - 11 + 1{1'b0}}, value[11 - 1: 0] };
				temp2 <= value >> 11;
				result <= {temp[11 - 1: 0] , temp2[15 - 11: 0]};
				end
			12:
				begin
				temp <= { {15 - 12 + 1{1'b0}}, value[12 - 1: 0] };
				temp2 <= value >> 12;
				result <= {temp[12 - 1: 0] , temp2[15 - 12: 0]};
				end
			13:
				begin
				temp <= { {15 - 13 + 1{1'b0}}, value[13 - 1: 0] };
				temp2 <= value >> 13;
				result <= {temp[13 - 1: 0] , temp2[15 - 13: 0]};
				end
			14:
				begin
				temp <= { {15 - 14 + 1{1'b0}}, value[14 - 1: 0] };
				temp2 <= value >> 14;
				result <= {temp[14 - 1: 0] , temp2[15 - 14: 0]};
				end
			15:
				begin
				temp <= { {15 - 15 + 1{1'b0}}, value[15 - 1: 0] };
				temp2 <= value >> 15;
				result <= {temp[15 - 1: 0] , temp2[15 - 15: 0]};
				end
		endcase
	end
endmodule

module rotate_left(n, value, result);
	input [15:0] n, value;
	output reg [15:0] result;
	reg [15:0] temp, temp2;
	
	always@(*)
	begin
		case(n[3:0])
			0:
				begin
				result <= value;
				end
			1:
				begin
				temp <= { {15 - 1 + 1{1'b0}}, value[15:15 - 1 + 1] };
				temp2 <= value << 1;
				result <= {temp2[15:1] , temp[1 - 1:0]};
				end
			2:
				begin
				temp <= { {15 - 2 + 1{1'b0}}, value[15:15 - 2 + 1] };
				temp2 <= value << 2;
				result <= {temp2[15:2] , temp[2 - 1:0]};
				end
			3:
				begin
				temp <= { {15 - 3 + 1{1'b0}}, value[15:15 - 3 + 1] };
				temp2 <= value << 3;
				result <= {temp2[15:3] , temp[3 - 1:0]};
				end
			4:
				begin
				temp <= { {15 - 4 + 1{1'b0}}, value[15:15 - 4 + 1] };
				temp2 <= value << 4;
				result <= {temp2[15:4] , temp[4 - 1:0]};
				end
			5:
				begin
				temp <= { {15 - 5 + 1{1'b0}}, value[15:15 - 5 + 1] };
				temp2 <= value << 5;
				result <= {temp2[15:5] , temp[5 - 1:0]};
				end
			6:
				begin
				temp <= { {15 - 6 + 1{1'b0}}, value[15:15 - 6 + 1] };
				temp2 <= value << 6;
				result <= {temp2[15:6] , temp[6 - 1:0]};
				end
			7:
				begin
				temp <= { {15 - 7 + 1{1'b0}}, value[15:15 - 7 + 1] };
				temp2 <= value << 7;
				result <= {temp2[15:7] , temp[7 - 1:0]};
				end
			8:
				begin
				temp <= { {15 - 8 + 1{1'b0}}, value[15:15 - 8 + 1] };
				temp2 <= value << 8;
				result <= {temp2[15:8] , temp[8 - 1:0]};
				end
			9:
				begin
				temp <= { {15 - 9 + 1{1'b0}}, value[15:15 - 9 + 1] };
				temp2 <= value << 9;
				result <= {temp2[15:9] , temp[9 - 1:0]};
				end
			10:
				begin
				temp <= { {15 - 10 + 1{1'b0}}, value[15:15 - 10 + 1] };
				temp2 <= value << 10;
				result <= {temp2[15:10] , temp[10 - 1:0]};
				end
			11:
				begin
				temp <= { {15 - 11 + 1{1'b0}}, value[15:15 - 11 + 1] };
				temp2 <= value << 11;
				result <= {temp2[15:11] , temp[11 - 1:0]};
				end
			12:
				begin
				temp <= { {15 - 12 + 1{1'b0}}, value[15:15 - 12 + 1] };
				temp2 <= value << 12;
				result <= {temp2[15:12] , temp[12 - 1:0]};
				end
			13:
				begin
				temp <= { {15 - 13 + 1{1'b0}}, value[15:15 - 13 + 1] };
				temp2 <= value << 13;
				result <= {temp2[15:13] , temp[13 - 1:0]};
				end
			14:
				begin
				temp <= { {15 - 14 + 1{1'b0}}, value[15:15 - 14 + 1] };
				temp2 <= value << 14;
				result <= {temp2[15:14] , temp[14 - 1:0]};
				end
			15:
				begin
				temp <= { {15 - 15 + 1{1'b0}}, value[15:15 - 15 + 1] };
				temp2 <= value << 15;
				result <= {temp2[15:15] , temp[15 - 1:0]};
				end
		endcase
	end
endmodule

alu.v
`timescale 1ns / 1ns
module alu(a,b,s,result,zero_detection);
input [15:0] a, b;
input [3:0] s;
output [15:0] result;
output reg zero_detection;
wire [15:0] rol_result, ror_result;
reg [15:0] other_result;
reg [1:0] mux_select;
wire [15:0] temp_result;

rotate_left rl1(.n(a), .value(b), .result(rol_result));
rotate_right rr1(.n(a), .value(b), .result(ror_result));
three_to_one_mux mux_1(.d0(rol_result),.d1(ror_result),.d2(other_result),.s(mux_select),.y(temp_result));

always@(a,b,s)
begin
 case(s)
      4'b1111: begin other_result = a + b; mux_select = 3'h2;end  // add
      4'b1110: begin other_result = a - b; mux_select = 3'h2;end // sub
      4'b1101: begin other_result = a & b; mux_select = 3'h2;end// and
      4'b1100: begin other_result = a | b; mux_select = 3'h2;end// or
      4'b0001: begin other_result = a * b; mux_select = 3'h2;end
      4'b1100: begin other_result = a / b; mux_select = 3'h2;end
      4'b1010: begin other_result = a<<b; mux_select = 3'h2;end
      4'b1011: begin other_result = a>>b; mux_select = 3'h2;end
      
      4'b1000:    begin 
                  if (a < b) 
                        begin 
                              other_result = 16'd1; 
                              mux_select = 3'h2; 
                        end
                  else
                        begin
                              other_result = 0;
                              mux_select = 3'h2; 
                        end
                  end 
      4'b1001:    begin 
                  if(a > b) 
                        begin
                              other_result = 16'd1; 
                              mux_select = 3'h2;
                        end
                  else
                        begin
                              other_result = 0;
                              mux_select = 3'h2; 
                        end
                  end
      4'b1001: begin mux_select = 3'h0;end
      4'b1010: begin mux_select = 3'h1; end
      
endcase      

if(result == 0)
      zero_detection = 1;
else
      zero_detection = 0;
end 

assign result = temp_result;
endmodule

alu_tb.v
`timescale 1ns / 1ns
module alu_tb;

reg [15:0] a, b;
reg [3:0] s;
wire [15:0] result;
wire zero_detection;

alu u1(a,b,s,result,zero_detection); 

initial 
    begin
        s = 0;
        a = 32'h0004;
        b = 32'h0005;
        #40
        s = 4'h1;
        #40
        s = 4'h2;
        #40
        s = 4'h3;
        #40
        s = 4'h4;
        #40
        s = 4'h5;
        #40
        s = 4'h6;
        #40
        s = 4'h7;
        #40
        s = 4'h8;
        #40
        s = 4'h9;
        #40
        s = 4'hA;
        #40
        s = 4'hB;
        #40
        s = 4'hC;
        #40 $stop; 
    end

initial 
    begin
		$dumpfile("alu.vcd");
		$dumpvars(0, alu_tb);
	end

endmodule

alu.vcd
$date
	Wed May 13 17:58:35 2020
$end
$version
	Icarus Verilog
$end
$timescale
	1ns
$end
$scope module alu_tb $end
$var wire 1 ! zero_detection $end
$var wire 16 " result [15:0] $end
$var reg 16 # a [15:0] $end
$var reg 16 $ b [15:0] $end
$var reg 4 % s [3:0] $end
$scope module u1 $end
$var wire 16 & a [15:0] $end
$var wire 16 ' b [15:0] $end
$var wire 16 ( result [15:0] $end
$var wire 4 ) s [3:0] $end
$var wire 16 * temp_result [15:0] $end
$var wire 16 + ror_result [15:0] $end
$var wire 16 , rol_result [15:0] $end
$var reg 2 - mux_select [1:0] $end
$var reg 16 . other_result [15:0] $end
$var reg 1 ! zero_detection $end
$scope module mux_1 $end
$var wire 16 / d2 [15:0] $end
$var wire 2 0 s [1:0] $end
$var wire 16 1 d1 [15:0] $end
$var wire 16 2 d0 [15:0] $end
$var reg 16 3 y [15:0] $end
$upscope $end
$scope module rl1 $end
$var wire 16 4 n [15:0] $end
$var wire 16 5 value [15:0] $end
$var reg 16 6 result [15:0] $end
$var reg 16 7 temp [15:0] $end
$var reg 16 8 temp2 [15:0] $end
$upscope $end
$scope module rr1 $end
$var wire 16 9 n [15:0] $end
$var wire 16 : value [15:0] $end
$var reg 16 ; result [15:0] $end
$var reg 16 < temp [15:0] $end
$var reg 16 = temp2 [15:0] $end
$upscope $end
$upscope $end
$upscope $end
$enddefinitions $end
#0
$dumpvars
b0 =
b101 <
b101000000000000 ;
b101 :
b100 9
b1010000 8
b0 7
b1010000 6
b101 5
b100 4
b1001 3
b1010000 2
b101000000000000 1
b10 0
b1001 /
b1001 .
b10 -
b1010000 ,
b101000000000000 +
b1001 *
b0 )
b1001 (
b101 '
b100 &
b0 %
b101 $
b100 #
b1001 "
0!
$end
#40
b1111111111111111 "
b1111111111111111 (
b1111111111111111 *
b1111111111111111 3
b1111111111111111 .
b1111111111111111 /
b1 %
b1 )
#80
b1111111111111011 "
b1111111111111011 (
b1111111111111011 *
b1111111111111011 3
b1111111111111011 .
b1111111111111011 /
b10 %
b10 )
#120
b10000000 "
b10000000 (
b10000000 *
b10000000 3
b10000000 .
b10000000 /
b11 %
b11 )
#160
b0 "
b0 (
b0 *
b0 3
b0 .
b0 /
b100 %
b100 )
#200
b100 "
b100 (
b100 *
b100 3
1!
b100 .
b100 /
b101 %
b101 )
#240
b101 "
b101 (
b101 *
b101 3
0!
b101 .
b101 /
b110 %
b110 )
#280
b1 "
b1 (
b1 *
b1 3
b1 .
b1 /
b111 %
b111 )
#320
b0 "
b0 (
b0 *
b0 3
b0 .
b0 /
b1000 %
b1000 )
#360
b1010000 "
b1010000 (
b1010000 *
b1010000 3
1!
b0 -
b0 0
b1001 %
b1001 )
#400
b101000000000000 "
b101000000000000 (
b101000000000000 *
b101000000000000 3
0!
b1 -
b1 0
b1010 %
b1010 )
#440
b10100 "
b10100 (
b10100 *
b10100 3
b10 -
b10 0
b10100 .
b10100 /
b1011 %
b1011 )
#480
b0 "
b0 (
b0 *
b0 3
b0 .
b0 /
b1100 %
b1100 )
