register_file.v
 `timescale 1ns / 1ns
 module register_file  
 (  
      input                    clk,  
      input                    rst,  
      // write port  
      input                    reg_write_en,  
      input          [3:0]     reg_write_dest,  
      input          [15:0]     reg_write_data,  
      //read port 1  
      input          [3:0]     reg_read_addr_1,  
      output          [15:0]     reg_read_data_1,  
      //read port 2  
      input          [3:0]     reg_read_addr_2,  
      output          [15:0]     reg_read_data_2  
 );  
      reg     [15:0]     reg_array [15:0];  
      // write port  
      //reg [2:0] i;  
      always @ (posedge clk or posedge rst) begin  
           if(rst) begin  
                reg_array[0] <= 16'h0;  
                reg_array[1] <= 16'h0F00;  
                reg_array[2] <= 16'h0050;  
                reg_array[3] <= 16'hFF0F;  
                reg_array[4] <= 16'hF0FF;  
                reg_array[5] <= 16'h0040;  
                reg_array[6] <= 16'h0024;  
                reg_array[7] <= 16'h00FF;
                reg_array[8] <= 16'hAAAA;
                reg_array[9] <= 16'h0000;
                reg_array[10] <= 16'h0000;
                reg_array[11] <= 16'h0000;
                reg_array[12] <= 16'hFFFF;
                reg_array[13] <= 16'h0002;
                reg_array[14] <= 16'h0000;
                reg_array[15] <= 16'h0000;

           end  
           else begin  
                if(reg_write_en) begin  
                     reg_array[reg_write_dest] <= reg_write_data;
                end  
           end  
      end  
      assign reg_read_data_1 = ( reg_read_addr_1 == 0)? 16'b0 : reg_array[reg_read_addr_1];  
      assign reg_read_data_2 = ( reg_read_addr_2 == 0)? 16'b0 : reg_array[reg_read_addr_2];  
 endmodule

register_file_tb.v
`timescale 1ns / 1ns
module register_file_tb;

reg clk, rst, reg_write_en;
reg[3:0] reg_read_addr_1, reg_read_addr_2, reg_write_dest;
reg[15:0] reg_write_data;
wire[15:0] reg_read_data_1, reg_read_data_2;
integer i;
register_file u1(clk, rst, reg_write_en,reg_write_dest, reg_write_data, reg_read_addr_1, reg_read_data_1, 
reg_read_addr_2, reg_read_data_2);  

always
#20 clk = ~clk;


initial
begin
    i = 0;
    clk = 0;
    rst = 1;
    reg_read_addr_1 = 0;
    reg_read_addr_2 = 0;
    reg_write_en = 0;
    reg_write_data = 16'h0666;
    reg_write_dest = 16'h0002;

    #10 rst = 0;
    
    for(i = 0; i < 4'hF; i = i+1)
        begin
            $display("Reading port 1... Register %d: %h", i, reg_read_data_1);
            $display("Reading port 2... Register %d: %h", i, reg_read_data_2);
            #2 reg_read_addr_1 = reg_read_addr_1 + 1; 
            #2 reg_read_addr_2 = reg_read_addr_2 + 1;
            #20;
        end
    reg_write_en = 1;
    #40 reg_write_en = 0; reg_read_addr_1 = 16'h0002;
    $display("Display written value: %h", reg_read_data_1); 
    #40 $stop;

end


initial begin
		$dumpfile("register_file.vcd");
		$dumpvars(0, register_file_tb);
	end
endmodule

register_file.vcd
$date
	Wed May 13 11:56:17 2020
$end
$version
	Icarus Verilog
$end
$timescale
	1ns
$end
$scope module register_file_tb $end
$var wire 16 ! reg_read_data_2 [15:0] $end
$var wire 16 " reg_read_data_1 [15:0] $end
$var reg 1 # clk $end
$var reg 4 $ reg_read_addr_1 [3:0] $end
$var reg 4 % reg_read_addr_2 [3:0] $end
$var reg 16 & reg_write_data [15:0] $end
$var reg 4 ' reg_write_dest [3:0] $end
$var reg 1 ( reg_write_en $end
$var reg 1 ) rst $end
$var integer 32 * i [31:0] $end
$scope module u1 $end
$var wire 1 # clk $end
$var wire 4 + reg_read_addr_1 [3:0] $end
$var wire 4 , reg_read_addr_2 [3:0] $end
$var wire 16 - reg_write_data [15:0] $end
$var wire 4 . reg_write_dest [3:0] $end
$var wire 1 ( reg_write_en $end
$var wire 1 ) rst $end
$var wire 16 / reg_read_data_2 [15:0] $end
$var wire 16 0 reg_read_data_1 [15:0] $end
$upscope $end
$upscope $end
$enddefinitions $end
#0
$dumpvars
b0 0
b0 /
b10 .
b11001100110 -
b0 ,
b0 +
b0 *
1)
0(
b10 '
b11001100110 &
b0 %
b0 $
0#
b0 "
b0 !
$end
#10
0)
#12
b111100000000 "
b111100000000 0
b1 $
b1 +
#14
b111100000000 !
b111100000000 /
b1 %
b1 ,
#20
1#
#34
b1 *
#36
b1010000 "
b1010000 0
b10 $
b10 +
#38
b1010000 !
b1010000 /
b10 %
b10 ,
#40
0#
#58
b10 *
#60
b1111111100001111 "
b1111111100001111 0
b11 $
b11 +
1#
#62
b1111111100001111 !
b1111111100001111 /
b11 %
b11 ,
#80
0#
#82
b11 *
#84
b1111000011111111 "
b1111000011111111 0
b100 $
b100 +
#86
b1111000011111111 !
b1111000011111111 /
b100 %
b100 ,
#100
1#
#106
b100 *
#108
b1000000 "
b1000000 0
b101 $
b101 +
#110
b1000000 !
b1000000 /
b101 %
b101 ,
#120
0#
#130
b101 *
#132
b100100 "
b100100 0
b110 $
b110 +
#134
b100100 !
b100100 /
b110 %
b110 ,
#140
1#
#154
b110 *
#156
b11111111 "
b11111111 0
b111 $
b111 +
#158
b11111111 !
b11111111 /
b111 %
b111 ,
#160
0#
#178
b111 *
#180
b1010101010101010 "
b1010101010101010 0
b1000 $
b1000 +
1#
#182
b1010101010101010 !
b1010101010101010 /
b1000 %
b1000 ,
#200
0#
#202
b1000 *
#204
b0 "
b0 0
b1001 $
b1001 +
#206
b0 !
b0 /
b1001 %
b1001 ,
#220
1#
#226
b1001 *
#228
b1010 $
b1010 +
#230
b1010 %
b1010 ,
#240
0#
#250
b1010 *
#252
b1011 $
b1011 +
#254
b1011 %
b1011 ,
#260
1#
#274
b1011 *
#276
b1111111111111111 "
b1111111111111111 0
b1100 $
b1100 +
#278
b1111111111111111 !
b1111111111111111 /
b1100 %
b1100 ,
#280
0#
#298
b1100 *
#300
b10 "
b10 0
b1101 $
b1101 +
1#
#302
b10 !
b10 /
b1101 %
b1101 ,
#320
0#
#322
b1101 *
#324
b0 "
b0 0
b1110 $
b1110 +
#326
b0 !
b0 /
b1110 %
b1110 ,
#340
1#
#346
b1110 *
#348
b1111 $
b1111 +
#350
b1111 %
b1111 ,
#360
0#
#370
1(
b1111 *
#380
1#
#400
0#
#410
b11001100110 "
b11001100110 0
b10 $
b10 +
0(
